verilog/mux2.v
module mux2 (
	in0,
	in1,
	sel,
	out
);
	parameter signed [31:0] WIDTH = 16;
	input [WIDTH - 1:0] in0;
	input [WIDTH - 1:0] in1;
	input sel;
	output wire [WIDTH - 1:0] out;
	assign out = (sel ? in1 : in0);
endmodule

sim_build/dump.vcd
$version Generated by VerilatedVcd $end
$timescale 1ps $end
 $scope module $rootio $end
  $var wire 16 # in0 [15:0] $end
  $var wire 16 $ in1 [15:0] $end
  $var wire 1 % sel $end
  $var wire 16 & out [15:0] $end
 $upscope $end
 $scope module mux2 $end
  $var wire 32 + WIDTH [31:0] $end
  $var wire 16 ' in0 [15:0] $end
  $var wire 16 ( in1 [15:0] $end
  $var wire 1 ) sel $end
  $var wire 16 * out [15:0] $end
 $upscope $end
$enddefinitions $end


#0
b1110100011000011 #
b1011011010000101 $
1%
b1011011010000101 &
b1110100011000011 '
b1011011010000101 (
1)
b1011011010000101 *
b00000000000000000000000000010000 +
#1000
b0110111110110111 #
b1010010000110110 $
b1010010000110110 &
b0110111110110111 '
b1010010000110110 (
b1010010000110110 *
#2000
b0110110100101110 #
b1111101100010111 $
b1111101100010111 &
b0110110100101110 '
b1111101100010111 (
b1111101100010111 *
#3000
b1001100100001111 #
b0110110010011000 $
0%
b1001100100001111 &
b1001100100001111 '
b0110110010011000 (
0)
b1001100100001111 *
#4000
b0100101111111111 #
b1101111100110101 $
b0100101111111111 &
b0100101111111111 '
b1101111100110101 (
b0100101111111111 *
#5000
b0100110001000001 #
b0101101100111111 $
b0100110001000001 &
b0100110001000001 '
b0101101100111111 (
b0100110001000001 *
#6000
b1100101100010000 #
b0110111100111100 $
b1100101100010000 &
b1100101100010000 '
b0110111100111100 (
b1100101100010000 *
#7000
b0100100000000110 #
b0011001010011111 $
1%
b0011001010011111 &
b0100100000000110 '
b0011001010011111 (
1)
b0011001010011111 *
#8000
b0011010010001001 #
b1000110011001100 $
0%
b0011010010001001 &
b0011010010001001 '
b1000110011001100 (
0)
b0011010010001001 *
#9000
b0010001110100110 #
b1110010101011010 $
1%
b1110010101011010 &
b0010001110100110 '
b1110010101011010 (
1)
b1110010101011010 *
#10000
b1001111100101000 #
b1000000010101010 $
0%
b1001111100101000 &
b1001111100101000 '
b1000000010101010 (
0)
b1001111100101000 *
#11000
b0100010100111011 #
b1000000100001111 $
1%
b1000000100001111 &
b0100010100111011 '
b1000000100001111 (
1)
b1000000100001111 *
#12000
b1010011010100010 #
b0111011010000110 $
b0111011010000110 &
b1010011010100010 '
b0111011010000110 (
b0111011010000110 *
#13000
b0110111010111010 #
b1010011111011111 $
0%
b0110111010111010 &
b0110111010111010 '
b1010011111011111 (
0)
b0110111010111010 *
#14000
b0010011001010101 #
b1010101000110100 $
b0010011001010101 &
b0010011001010101 '
b1010101000110100 (
b0010011001010101 *
#15000
b0111100001111001 #
b1000010010000100 $
1%
b1000010010000100 &
b0111100001111001 '
b1000010010000100 (
1)
b1000010010000100 *
#16000
b1000010000001011 #
b1111110111101111 $
0%
b1000010000001011 &
b1000010000001011 '
b1111110111101111 (
0)
b1000010000001011 *
#17000
b0101010010110011 #
b0011101100000110 $
1%
b0011101100000110 &
b0101010010110011 '
b0011101100000110 (
1)
b0011101100000110 *
#18000
b0110101010001110 #
b1011001110101001 $
0%
b0110101010001110 &
b0110101010001110 '
b1011001110101001 (
0)
b0110101010001110 *
#19000
b0011001110111000 #
b0110111111011001 $
1%
b0110111111011001 &
b0011001110111000 '
b0110111111011001 (
1)
b0110111111011001 *
#20000
b1111110111110111 #
b1000101000101010 $
0%
b1111110111110111 &
b1111110111110111 '
b1000101000101010 (
0)
b1111110111110111 *
#21000
b1110110101100101 #
b1010101111101111 $
1%
b1010101111101111 &
b1110110101100101 '
b1010101111101111 (
1)
b1010101111101111 *
#22000
b0010011010010001 #
b1011001000001010 $
0%
b0010011010010001 &
b0010011010010001 '
b1011001000001010 (
0)
b0010011010010001 *
#23000
b1101010010100110 #
b0010001011110110 $
b1101010010100110 &
b1101010010100110 '
b0010001011110110 (
b1101010010100110 *
#24000
b0101000000001000 #
b1010010101100011 $
b0101000000001000 &
b0101000000001000 '
b1010010101100011 (
b0101000000001000 *
#25000
b1111101011010011 #
b0001011001001011 $
1%
b0001011001001011 &
b1111101011010011 '
b0001011001001011 (
1)
b0001011001001011 *
#26000
b1100101011111000 #
b1100111001001011 $
0%
b1100101011111000 &
b1100101011111000 '
b1100111001001011 (
0)
b1100101011111000 *
#27000
b0111110001100110 #
b0000110110110100 $
1%
b0000110110110100 &
b0111110001100110 '
b0000110110110100 (
1)
b0000110110110100 *
#28000
b1101001001011111 #
b1100011010010001 $
0%
b1101001001011111 &
b1101001001011111 '
b1100011010010001 (
0)
b1101001001011111 *
#29000
b0010101000110100 #
b1101000000001111 $
1%
b1101000000001111 &
b0010101000110100 '
b1101000000001111 (
1)
b1101000000001111 *
#30000
b0010110110100010 #
b0100011001010111 $
0%
b0010110110100010 &
b0010110110100010 '
b0100011001010111 (
0)
b0010110110100010 *
#31000
b0101000010110110 #
b1011100001001000 $
1%
b1011100001001000 &
b0101000010110110 '
b1011100001001000 (
1)
b1011100001001000 *
#32000
b0011001111111101 #
b0010111001010011 $
b0010111001010011 &
b0011001111111101 '
b0010111001010011 (
b0010111001010011 *
#33000
b1000101110001011 #
b1111001110101010 $
b1111001110101010 &
b1000101110001011 '
b1111001110101010 (
b1111001110101010 *
#34000
b1001011010101000 #
b1011111110010000 $
b1011111110010000 &
b1001011010101000 '
b1011111110010000 (
b1011111110010000 *
#35000
b1100111001000001 #
b0100010010100101 $
b0100010010100101 &
b1100111001000001 '
b0100010010100101 (
b0100010010100101 *
#36000
b0101010011111110 #
b1011000011011110 $
0%
b0101010011111110 &
b0101010011111110 '
b1011000011011110 (
0)
b0101010011111110 *
#37000
b0010010101000000 #
b1011011010111011 $
b0010010101000000 &
b0010010101000000 '
b1011011010111011 (
b0010010101000000 *
#38000
b0011110001110011 #
b1101111100110011 $
b0011110001110011 &
b0011110001110011 '
b1101111100110011 (
b0011110001110011 *
#39000
b0010010101101101 #
b1000000100101011 $
b0010010101101101 &
b0010010101101101 '
b1000000100101011 (
b0010010101101101 *
#40000
b1011101001111011 #
b0110001000101010 $
1%
b0110001000101010 &
b1011101001111011 '
b0110001000101010 (
1)
b0110001000101010 *
#41000
b1101101010000110 #
b0111010110111001 $
0%
b1101101010000110 &
b1101101010000110 '
b0111010110111001 (
0)
b1101101010000110 *
#42000
b1100001000110000 #
b0100011010011011 $
b1100001000110000 &
b1100001000110000 '
b0100011010011011 (
b1100001000110000 *
#43000
b0011110010001001 #
b0101001000011110 $
1%
b0101001000011110 &
b0011110010001001 '
b0101001000011110 (
1)
b0101001000011110 *
#44000
b0000100101110010 #
b0001110010101011 $
b0001110010101011 &
b0000100101110010 '
b0001110010101011 (
b0001110010101011 *
#45000
b0100001100000110 #
b1010110010011111 $
b1010110010011111 &
b0100001100000110 '
b1010110010011111 (
b1010110010011111 *
#46000
b0010000000100011 #
b0010010000001101 $
0%
b0010000000100011 &
b0010000000100011 '
b0010010000001101 (
0)
b0010000000100011 *
#47000
b1011000011011101 #
b1110110010100110 $
1%
b1110110010100110 &
b1011000011011101 '
b1110110010100110 (
1)
b1110110010100110 *
#48000
b0010010110110110 #
b0100111011000111 $
0%
b0010010110110110 &
b0010010110110110 '
b0100111011000111 (
0)
b0010010110110110 *
#49000
b0000110110111000 #
b0111010000110011 $
b0000110110111000 &
b0000110110111000 '
b0111010000110011 (
b0000110110111000 *
#50000
b1101011111010011 #
b1001010110110011 $
b1101011111010011 &
b1101011111010011 '
b1001010110110011 (
b1101011111010011 *
#51000
b0100101101000100 #
b1011001011001111 $
b0100101101000100 &
b0100101101000100 '
b1011001011001111 (
b0100101101000100 *
#52000
b1011100011110000 #
b1110011110110011 $
b1011100011110000 &
b1011100011110000 '
b1110011110110011 (
b1011100011110000 *
#53000
b0010110110001000 #
b0100010000011101 $
b0010110110001000 &
b0010110110001000 '
b0100010000011101 (
b0010110110001000 *
#54000
b1101100100110110 #
b1100100010001101 $
b1101100100110110 &
b1101100100110110 '
b1100100010001101 (
b1101100100110110 *
#55000
b0011111111010001 #
b1001100101111110 $
b0011111111010001 &
b0011111111010001 '
b1001100101111110 (
b0011111111010001 *
#56000
b0010011100111001 #
b0010110111011001 $
b0010011100111001 &
b0010011100111001 '
b0010110111011001 (
b0010011100111001 *
#57000
b0010010000111110 #
b0010111101010101 $
1%
b0010111101010101 &
b0010010000111110 '
b0010111101010101 (
1)
b0010111101010101 *
#58000
b0111010111111010 #
b0010101100000111 $
0%
b0111010111111010 &
b0111010111111010 '
b0010101100000111 (
0)
b0111010111111010 *
#59000
b1100101000001001 #
b1000011011110001 $
b1100101000001001 &
b1100101000001001 '
b1000011011110001 (
b1100101000001001 *
#60000
b1100101011011001 #
b1011001110101110 $
1%
b1011001110101110 &
b1100101011011001 '
b1011001110101110 (
1)
b1011001110101110 *
#61000
b0101100111010111 #
b1110001010111000 $
b1110001010111000 &
b0101100111010111 '
b1110001010111000 (
b1110001010111000 *
#62000
b1011001100010011 #
b1001110000100101 $
b1001110000100101 &
b1011001100010011 '
b1001110000100101 (
b1001110000100101 *
#63000
b0001010000111011 #
b1011110000111111 $
b1011110000111111 &
b0001010000111011 '
b1011110000111111 (
b1011110000111111 *
#64000
b1011100111101001 #
b0101110111011010 $
b0101110111011010 &
b1011100111101001 '
b0101110111011010 (
b0101110111011010 *
#65000
b0110010111000111 #
b0101100001111010 $
b0101100001111010 &
b0110010111000111 '
b0101100001111010 (
b0101100001111010 *
#66000
b1101110100000010 #
b0011011001111101 $
b0011011001111101 &
b1101110100000010 '
b0011011001111101 (
b0011011001111101 *
#67000
b0011000111001110 #
b0111000100001110 $
b0111000100001110 &
b0011000111001110 '
b0111000100001110 (
b0111000100001110 *
#68000
b1111011101010100 #
b1110000100001111 $
b1110000100001111 &
b1111011101010100 '
b1110000100001111 (
b1110000100001111 *
#69000
b0011111110100010 #
b1010001010010111 $
0%
b0011111110100010 &
b0011111110100010 '
b1010001010010111 (
0)
b0011111110100010 *
#70000
b0101001001101011 #
b0010000110110010 $
b0101001001101011 &
b0101001001101011 '
b0010000110110010 (
b0101001001101011 *
#71000
b1101011100011101 #
b0011000010110000 $
1%
b0011000010110000 &
b1101011100011101 '
b0011000010110000 (
1)
b0011000010110000 *
#72000
b1101110010011011 #
b0111011101100001 $
0%
b1101110010011011 &
b1101110010011011 '
b0111011101100001 (
0)
b1101110010011011 *
#73000
b0101110111100100 #
b1100010100011001 $
b0101110111100100 &
b0101110111100100 '
b1100010100011001 (
b0101110111100100 *
#74000
b0111111011101111 #
b0101111001010001 $
b0111111011101111 &
b0111111011101111 '
b0101111001010001 (
b0111111011101111 *
#75000
b0111100110100001 #
b0000011100111111 $
b0111100110100001 &
b0111100110100001 '
b0000011100111111 (
b0111100110100001 *
#76000
b0101011111100000 #
b1001100111111101 $
b0101011111100000 &
b0101011111100000 '
b1001100111111101 (
b0101011111100000 *
#77000
b0101010001111101 #
b1001100100110110 $
1%
b1001100100110110 &
b0101010001111101 '
b1001100100110110 (
1)
b1001100100110110 *
#78000
b0010001010001001 #
b0111001111001010 $
0%
b0010001010001001 &
b0010001010001001 '
b0111001111001010 (
0)
b0010001010001001 *
#79000
b0101001101010011 #
b0110110010110101 $
1%
b0110110010110101 &
b0101001101010011 '
b0110110010110101 (
1)
b0110110010110101 *
#80000
b1011011001111101 #
b1111010101010001 $
b1111010101010001 &
b1011011001111101 '
b1111010101010001 (
b1111010101010001 *
#81000
b1100100110111110 #
b0010001110111010 $
b0010001110111010 &
b1100100110111110 '
b0010001110111010 (
b0010001110111010 *
#82000
b1100010000100010 #
b1100100110011010 $
0%
b1100010000100010 &
b1100010000100010 '
b1100100110011010 (
0)
b1100010000100010 *
#83000
b1000000010000010 #
b0110011100101001 $
b1000000010000010 &
b1000000010000010 '
b0110011100101001 (
b1000000010000010 *
#84000
b1101010100011001 #
b1111111110011010 $
1%
b1111111110011010 &
b1101010100011001 '
b1111111110011010 (
1)
b1111111110011010 *
#85000
b0101010111000001 #
b0011110011110011 $
0%
b0101010111000001 &
b0101010111000001 '
b0011110011110011 (
0)
b0101010111000001 *
#86000
b1110101101011000 #
b1110101101001101 $
1%
b1110101101001101 &
b1110101101011000 '
b1110101101001101 (
1)
b1110101101001101 *
#87000
b0011111100100111 #
b0111100100011011 $
b0111100100011011 &
b0011111100100111 '
b0111100100011011 (
b0111100100011011 *
#88000
b1001110010001011 #
b0011010111110100 $
b0011010111110100 &
b1001110010001011 '
b0011010111110100 (
b0011010111110100 *
#89000
b0101011001111000 #
b0110011001000010 $
0%
b0101011001111000 &
b0101011001111000 '
b0110011001000010 (
0)
b0101011001111000 *
#90000
b0001001010010111 #
b0000010101011100 $
b0001001010010111 &
b0001001010010111 '
b0000010101011100 (
b0001001010010111 *
#91000
b1011111001101001 #
b0001110011011101 $
1%
b0001110011011101 &
b1011111001101001 '
b0001110011011101 (
1)
b0001110011011101 *
#92000
b1101101110111011 #
b0001000000011001 $
0%
b1101101110111011 &
b1101101110111011 '
b0001000000011001 (
0)
b1101101110111011 *
#93000
b1001010110111000 #
b0101110000011100 $
1%
b0101110000011100 &
b1001010110111000 '
b0101110000011100 (
1)
b0101110000011100 *
#94000
b0011010110100001 #
b1101010010011101 $
0%
b0011010110100001 &
b0011010110100001 '
b1101010010011101 (
0)
b0011010110100001 *
#95000
b1101010110101100 #
b1100010011101001 $
1%
b1100010011101001 &
b1101010110101100 '
b1100010011101001 (
1)
b1100010011101001 *
#96000
b1000001110001011 #
b0011100100100101 $
0%
b1000001110001011 &
b1000001110001011 '
b0011100100100101 (
0)
b1000001110001011 *
#97000
b0111110001111000 #
b1000111011000110 $
b0111110001111000 &
b0111110001111000 '
b1000111011000110 (
b0111110001111000 *
#98000
b1100101101001000 #
b0101111110110001 $
b1100101101001000 &
b1100101101001000 '
b0101111110110001 (
b1100101101001000 *
#99000
b1101110101100101 #
b1101010010001111 $
1%
b1101010010001111 &
b1101110101100101 '
b1101010010001111 (
1)
b1101010010001111 *
